pyaxe_pandas/__init__.py
pyaxe_pandas/operation.py
pyaxe_pandas-2020.8.18.dist-info/LICENSE
pyaxe_pandas-2020.8.18.dist-info/METADATA
pyaxe_pandas-2020.8.18.dist-info/WHEEL
pyaxe_pandas-2020.8.18.dist-info/top_level.txt
pyaxe_pandas-2020.8.18.dist-info/RECORD
