Metadata-Version: 2.1
Name: pyaxe-pandas
Version: 2020.8.18
Summary: 对pandas进行配置文件操作，用yml文件对pandas进行操作，无须写一行代码即可分析数据。
Home-page: https://github.com/pyaxe/pyaxe-pandas
Author: Jtyoui
Author-email: jtyoui@qq.com
License: MIT Licence
Platform: any
Classifier: Programming Language :: Python :: 3
Classifier: License :: OSI Approved :: MIT License
Classifier: Operating System :: OS Independent
Requires-Dist: pyyaml
